{
    "asset": {
        "format": "JPG",
        "id": "b769c2866257a5b21109d1c8cf341702",
        "name": "PICT0008.JPG",
        "path": "file:/Users/michaeltang/Downloads/TrainYourOwnTOLO/Data/Source%20Images/Training_Images/PICT0008.JPG",
        "size": {
            "width": 2976,
            "height": 2232
        },
        "state": 2,
        "type": 1
    },
    "regions": [
        {
            "id": "a_yq-QCWA",
            "type": "RECTANGLE",
            "tags": [
                "bar"
            ],
            "boundingBox": {
                "height": 719.3494821903856,
                "width": 1585.6323617788462,
                "left": 157.5145733173077,
                "top": 115.21579245301302
            },
            "points": [
                {
                    "x": 157.5145733173077,
                    "y": 115.21579245301302
                },
                {
                    "x": 1743.146935096154,
                    "y": 115.21579245301302
                },
                {
                    "x": 1743.146935096154,
                    "y": 834.5652746433987
                },
                {
                    "x": 157.5145733173077,
                    "y": 834.5652746433987
                }
            ]
        }
    ],
    "version": "2.2.0"
}